hurley_generic_plot/__init__.py
hurley_generic_plot/clinical.py
hurley_generic_plot/generic.py
hurley_generic_plot-4.dist-info/METADATA
hurley_generic_plot-4.dist-info/WHEEL
hurley_generic_plot-4.dist-info/licenses/LICENSE
hurley_generic_plot-4.dist-info/RECORD
