Metadata-Version: 2.3
Name: hurley-generic-plot
Version: 4
Summary: Just some generic functions to make plots
Project-URL: Homepage, https://github.com/hurleyLi/generic-plot
Project-URL: Bug Tracker, https://github.com/hurleyLi/generic-plot/issues
Author-email: Hurley Li <lihe.oscar@gmail.com>
License: MIT
Classifier: License :: OSI Approved :: MIT License
Classifier: Operating System :: OS Independent
Classifier: Programming Language :: Python :: 3
Requires-Python: >=3.7
